setup.py
searchscrapeserver/__init__.py
searchscrapeserver.egg-info/PKG-INFO
searchscrapeserver.egg-info/SOURCES.txt
searchscrapeserver.egg-info/dependency_links.txt
searchscrapeserver.egg-info/not-zip-safe
searchscrapeserver.egg-info/requires.txt
searchscrapeserver.egg-info/top_level.txt
searchscrapeserver/common/bing_urls.py
searchscrapeserver/common/exceptions.py
searchscrapeserver/common/google_urls.py
searchscrapeserver/common/headers.py
searchscrapeserver/common/yandex_urls.py
searchscrapeserver/parsing/bing_result_parser.py
searchscrapeserver/parsing/google_result_parser.py
searchscrapeserver/parsing/yandex_result_parser.py
searchscrapeserver/schemas/google_schemas.py
searchscrapeserver/scraping/bing_scraping.py
searchscrapeserver/scraping/google_scraping.py
searchscrapeserver/scraping/yandex_scraping.py
searchscrapeserver/server/server.py