Metadata-Version: 1.1
Name: searchscrapeserver
Version: 0.2.5.3
Summary: Server implementation scraping a number of popular servers
Home-page: https://github.com/EdmundMartin/SearchScraperAPI
Author: Edmund Martin
Author-email: edmartin101@googlemail.com
License: GPL-3.0
Download-URL: https://github.com/EdmundMartin/SearchScraperAPI/archive/0.2.5.2.tar.gz
Platform: UNKNOWN
